[
  {
    "q": "Apa itu penipuan online?",
    "a": "Penipuan online adalah ketika seseorang berusaha mengambil uang atau data dengan cara yang tidak jujur melalui internet."
  },
  {
    "q": "Mengapa tidak boleh membagikan nomor kartu ATM atau OTP?",
    "a": "Nomor kartu ATM dan OTP adalah rahasia bank. Jika orang lain tahu, uang di rekening bisa hilang."
  },
  {
    "q": "Apa yang harus dilakukan jika ditawari hadiah besar di internet?",
    "a": "Jangan langsung percaya. Biasanya itu penipuan. Tanyakan pada orang tua sebelum mengikuti."
  },
  {
    "q": "Bagaimana cara belanja online dengan aman?",
    "a": "Gunakan situs atau aplikasi terpercaya, jangan transfer ke rekening pribadi yang mencurigakan, dan tanyakan pada orang dewasa jika ragu."
  },
  {
    "q": "Apakah boleh meminjamkan uang kepada teman online?",
    "a": "Lebih baik tidak, terutama jika kamu belum pernah bertemu langsung. Ceritakan pada orang tua terlebih dahulu."
  }
]
